pyasyncagent/__init__.py
pyasyncagent/agent/__init__.py
pyasyncagent/agent/async_agent.py
pyasyncagent/data_model/__init__.py
pyasyncagent/data_model/iris.py
pyasyncagent/data_model/utils.py
pyasyncagent/kg_operations/__init__.py
pyasyncagent/kg_operations/gateway.py
pyasyncagent/kg_operations/sparql_client.py
tests/__init__.py
tests/random_agent.py
tests/sparql_client_for_test.py
tests/test_async_agent.py
tests/resources/Service__Random.ttl
tests/resources/dummy_abox.ttl
tests/resources/dummy_tbox.ttl
pyasyncagent-0.0.5.dist-info/LICENSE
pyasyncagent-0.0.5.dist-info/METADATA
pyasyncagent-0.0.5.dist-info/WHEEL
pyasyncagent-0.0.5.dist-info/top_level.txt
pyasyncagent-0.0.5.dist-info/RECORD
