Metadata-Version: 2.1
Name: pyasyncagent
Version: 0.0.5
Summary: pyasyncagent is a python wrapper for asynchronous agents as part of The World Avatar project.
Home-page: https://github.com/cambridge-cares/TheWorldAvatar/tree/142-dev-python-async-agent/JPS_BASE_LIB/python_async_agent
Author: Jiaru Bai
Author-email: jb2197@cam.ac.uk
License: MIT
Platform: UNKNOWN
Requires-Python: >=3.5
License-File: LICENSE
Requires-Dist: py4jps (>=1.0.17)
Requires-Dist: flask (==1.1.2)
Requires-Dist: gunicorn (==20.0.4)
Requires-Dist: Flask-APScheduler
Requires-Dist: rdflib
Provides-Extra: dev
Requires-Dist: testcontainers (>=3.4.2) ; extra == 'dev'
Requires-Dist: pytest (>=6.2.3) ; extra == 'dev'
